sidekick/__init__.py
sidekick/admin.py
sidekick/apps.py
sidekick/decorators.py
sidekick/models.py
sidekick/migrations/0001_initial.py
sidekick/migrations/0002_create_common_cron.py
sidekick/migrations/0003_update_task_model.py
sidekick/migrations/0004_add_status_created_finished_fields.py
sidekick/migrations/__init__.py
sidekick/services/__init__.py
sidekick/services/cron_files.py
sidekick/services/cron_schedule.py
sidekick/services/crontab.py
sidekick/services/helpers.py
sidekick/signals/__init__.py
sidekick/signals/pre_delete.py
side_kick-0.1.16.dist-info/LICENSE
side_kick-0.1.16.dist-info/METADATA
side_kick-0.1.16.dist-info/WHEEL
side_kick-0.1.16.dist-info/top_level.txt
side_kick-0.1.16.dist-info/RECORD
