Metadata-Version: 2.1
Name: side-kick
Version: 0.1.16
Summary: A lightweight task runner for django with easy admin controls
Home-page: https://github.com/CurrieBen/sidekick
Author: Ben Currie
Author-email: benjamin.w.currie@gmail.com
License: MIT License
Platform: UNKNOWN
Classifier: Programming Language :: Python :: 3
Classifier: License :: OSI Approved :: MIT License
Classifier: Operating System :: OS Independent
